{
  "table_of_contents": [
    {
      "title": "TECHNOLOGICAL UNIVERSITY DUBLIN",
      "heading_level": null,
      "page_id": 0,
      "polygon": [
        [
          124.80900645256042,
          171.42360028624535
        ],
        [
          474.0,
          171.42360028624535
        ],
        [
          474.0,
          191.3093897998333
        ],
        [
          124.80900645256042,
          191.3093897998333
        ]
      ]
    },
    {
      "title": "TU856 B.Sc. (Hons) Computer Science \nTU857 B.Sc. (Hons) Computer Science (Infrastructure) \nTU858 B.Sc (Hons) Computer Science International \nDT844 Erasmus",
      "heading_level": null,
      "page_id": 0,
      "polygon": [
        [
          97.7061870098114,
          247.20283794403076
        ],
        [
          502.0,
          247.20283794403076
        ],
        [
          502.0,
          330.0028885602951
        ],
        [
          97.7061870098114,
          330.0028885602951
        ]
      ]
    },
    {
      "title": "CMPU3010 Databases 2",
      "heading_level": null,
      "page_id": 0,
      "polygon": [
        [
          226.75666093826294,
          440.9472185373306
        ],
        [
          372.0,
          440.9472185373306
        ],
        [
          372.0,
          457.1063641309738
        ],
        [
          226.75666093826294,
          457.1063641309738
        ]
      ]
    },
    {
      "title": "Instructions To Candidates:",
      "heading_level": null,
      "page_id": 0,
      "polygon": [
        [
          44.97656786441803,
          597.1172118186951
        ],
        [
          217.0,
          597.1172118186951
        ],
        [
          217.0,
          612.0
        ],
        [
          44.97656786441803,
          612.0
        ]
      ]
    },
    {
      "title": "City Bikes Case Study Description",
      "heading_level": null,
      "page_id": 1,
      "polygon": [
        [
          197.3773511648178,
          101.13311365246773
        ],
        [
          395.76675605773926,
          101.13311365246773
        ],
        [
          395.76675605773926,
          116.16450467705727
        ],
        [
          197.3773511648178,
          116.16450467705727
        ]
      ]
    },
    {
      "title": "Figure 1 Entity Relationship Diagram for City Bikes",
      "heading_level": null,
      "page_id": 2,
      "polygon": [
        [
          58.376110911369324,
          369.3544265627861
        ],
        [
          286.2145599126816,
          367.7098953127861
        ],
        [
          286.2145599126816,
          380.18304854631424
        ],
        [
          58.376110911369324,
          381.82757979631424
        ]
      ]
    },
    {
      "title": "Question 1 (compulsory) [40 marks]",
      "heading_level": null,
      "page_id": 2,
      "polygon": [
        [
          45.0,
          393.0
        ],
        [
          550.0,
          391.5446576476097
        ],
        [
          550.0,
          405.0
        ],
        [
          45.0,
          405.9568902850151
        ]
      ]
    },
    {
      "title": "",
      "heading_level": null,
      "page_id": 2,
      "polygon": [
        [
          494.1860237121582,
          394.9916589856148
        ],
        [
          551.0117268562317,
          394.9916589856148
        ],
        [
          551.0117268562317,
          407.45522648096085
        ],
        [
          494.1860237121582,
          407.45522648096085
        ]
      ]
    },
    {
      "title": "Question 2 [30 marks]",
      "heading_level": null,
      "page_id": 3,
      "polygon": [
        [
          45.0,
          327.0
        ],
        [
          550.0,
          326.0695490241051
        ],
        [
          550.0,
          339.19478338956833
        ],
        [
          45.0,
          340.83931463956833
        ]
      ]
    },
    {
      "title": "",
      "heading_level": null,
      "page_id": 3,
      "polygon": [
        [
          493.8639597892761,
          325.81168764829636
        ],
        [
          551.0725445747375,
          325.81168764829636
        ],
        [
          551.0725445747375,
          338.42491310834885
        ],
        [
          493.8639597892761,
          338.42491310834885
        ]
      ]
    },
    {
      "title": "Weekly Maintenance work Report",
      "heading_level": null,
      "page_id": 4,
      "polygon": [
        [
          315.9239736199379,
          85.0
        ],
        [
          510.28748750686646,
          84.04247587919235
        ],
        [
          509.0,
          99.0
        ],
        [
          314.2794423699379,
          99.0
        ]
      ]
    },
    {
      "title": "Question 3 [30 marks]",
      "heading_level": null,
      "page_id": 5,
      "polygon": [
        [
          52.0,
          87.22129042446613
        ],
        [
          550.0,
          87.22129042446613
        ],
        [
          550.0,
          101.1264575868845
        ],
        [
          52.0,
          101.1264575868845
        ]
      ]
    },
    {
      "title": "",
      "heading_level": null,
      "page_id": 5,
      "polygon": [
        [
          493.81415462493896,
          87.4516931772232
        ],
        [
          551.13592004776,
          87.4516931772232
        ],
        [
          549.97185754776,
          100.53322711586952
        ],
        [
          492.65009212493896,
          100.53322711586952
        ]
      ]
    },
    {
      "title": "Table 3 Sample Customer Complaints",
      "heading_level": null,
      "page_id": 5,
      "polygon": [
        [
          222.20623803138733,
          228.99919492006302
        ],
        [
          389.6831724643707,
          228.99919492006302
        ],
        [
          389.6831724643707,
          241.6054443717003
        ],
        [
          222.20623803138733,
          241.6054443717003
        ]
      ]
    },
    {
      "title": "Question 4 [30 marks]",
      "heading_level": null,
      "page_id": 6,
      "polygon": [
        [
          44.26695528626442,
          77.09811729192734
        ],
        [
          550.0,
          77.09811729192734
        ],
        [
          550.0,
          91.10403507947922
        ],
        [
          43.10289278626442,
          91.10403507947922
        ]
      ]
    },
    {
      "title": "",
      "heading_level": null,
      "page_id": 6,
      "polygon": [
        [
          494.191458940506,
          76.27881270647049
        ],
        [
          551.0071442127228,
          76.27881270647049
        ],
        [
          549.8430817127228,
          89.90217924118042
        ],
        [
          493.027396440506,
          89.90217924118042
        ]
      ]
    },
    {
      "title": "END OF PAPER",
      "heading_level": null,
      "page_id": 6,
      "polygon": [
        [
          288.5742838382721,
          414.5544442534447
        ],
        [
          363.8930494785309,
          412.9099130034447
        ],
        [
          363.8930494785309,
          428.0
        ],
        [
          288.5742838382721,
          429.3931920528412
        ]
      ]
    },
    {
      "title": "SQL",
      "heading_level": null,
      "page_id": 7,
      "polygon": [
        [
          172.47933635115623,
          92.0
        ],
        [
          204.6367276608944,
          92.0
        ],
        [
          204.6367276608944,
          106.26730221509933
        ],
        [
          172.47933635115623,
          106.26730221509933
        ]
      ]
    },
    {
      "title": "PLPGSQL FUNCTION",
      "heading_level": null,
      "page_id": 7,
      "polygon": [
        [
          318.3353639245033,
          92.0
        ],
        [
          438.0,
          92.0
        ],
        [
          438.0,
          106.0
        ],
        [
          318.3353639245033,
          106.0
        ]
      ]
    },
    {
      "title": "PLPGSQL TRIGGER",
      "heading_level": null,
      "page_id": 7,
      "polygon": [
        [
          317.9898507595062,
          272.90507113933563
        ],
        [
          443.2166796922684,
          272.90507113933563
        ],
        [
          443.0,
          288.0
        ],
        [
          316.3453195095062,
          288.0
        ]
      ]
    },
    {
      "title": "PLPGSQL PROCEDURE",
      "heading_level": null,
      "page_id": 7,
      "polygon": [
        [
          319.0,
          345.0
        ],
        [
          448.73154056072235,
          345.0
        ],
        [
          447.08700931072235,
          359.41850662231445
        ],
        [
          317.9209940433502,
          359.41850662231445
        ]
      ]
    },
    {
      "title": "MONGODB EXAMPLES",
      "heading_level": null,
      "page_id": 7,
      "polygon": [
        [
          565.4546654224396,
          92.0
        ],
        [
          701.895854473114,
          92.0
        ],
        [
          701.895854473114,
          106.0
        ],
        [
          565.4546654224396,
          106.0
        ]
      ]
    }
  ],
  "page_stats": [
    {
      "page_id": 0,
      "text_extraction_method": "pdftext",
      "block_counts": [
        [
          "Span",
          75
        ],
        [
          "Line",
          31
        ],
        [
          "Text",
          11
        ],
        [
          "SectionHeader",
          4
        ],
        [
          "PageFooter",
          1
        ]
      ]
    },
    {
      "page_id": 1,
      "text_extraction_method": "pdftext",
      "block_counts": [
        [
          "Span",
          89
        ],
        [
          "Line",
          32
        ],
        [
          "Text",
          7
        ],
        [
          "PageHeader",
          1
        ],
        [
          "SectionHeader",
          1
        ],
        [
          "Picture",
          1
        ],
        [
          "PageFooter",
          1
        ]
      ]
    },
    {
      "page_id": 2,
      "text_extraction_method": "pdftext",
      "block_counts": [
        [
          "Span",
          67
        ],
        [
          "Line",
          18
        ],
        [
          "SectionHeader",
          3
        ],
        [
          "Text",
          2
        ],
        [
          "PageHeader",
          1
        ],
        [
          "Figure",
          1
        ],
        [
          "ListItem",
          1
        ],
        [
          "Table",
          1
        ],
        [
          "PageFooter",
          1
        ]
      ]
    },
    {
      "page_id": 3,
      "text_extraction_method": "pdftext",
      "block_counts": [
        [
          "Span",
          101
        ],
        [
          "Line",
          25
        ],
        [
          "Text",
          4
        ],
        [
          "ListItem",
          3
        ],
        [
          "SectionHeader",
          2
        ],
        [
          "PageHeader",
          1
        ],
        [
          "Table",
          1
        ],
        [
          "PageFooter",
          1
        ]
      ]
    },
    {
      "page_id": 4,
      "text_extraction_method": "pdftext",
      "block_counts": [
        [
          "Span",
          267
        ],
        [
          "Line",
          81
        ],
        [
          "PageHeader",
          1
        ],
        [
          "Table",
          1
        ],
        [
          "SectionHeader",
          1
        ],
        [
          "Text",
          1
        ],
        [
          "PageFooter",
          1
        ]
      ]
    },
    {
      "page_id": 5,
      "text_extraction_method": "pdftext",
      "block_counts": [
        [
          "Span",
          96
        ],
        [
          "Line",
          25
        ],
        [
          "ListItem",
          5
        ],
        [
          "SectionHeader",
          3
        ],
        [
          "Text",
          2
        ],
        [
          "ListGroup",
          2
        ],
        [
          "PageHeader",
          1
        ],
        [
          "Table",
          1
        ],
        [
          "PageFooter",
          1
        ]
      ]
    },
    {
      "page_id": 6,
      "text_extraction_method": "pdftext",
      "block_counts": [
        [
          "Span",
          71
        ],
        [
          "Line",
          21
        ],
        [
          "ListItem",
          6
        ],
        [
          "SectionHeader",
          3
        ],
        [
          "Text",
          3
        ],
        [
          "PageHeader",
          1
        ],
        [
          "PageFooter",
          1
        ],
        [
          "ListGroup",
          1
        ]
      ]
    },
    {
      "page_id": 7,
      "text_extraction_method": "pdftext",
      "block_counts": [
        [
          "Span",
          163
        ],
        [
          "Line",
          71
        ],
        [
          "Text",
          6
        ],
        [
          "SectionHeader",
          5
        ],
        [
          "PageHeader",
          1
        ],
        [
          "PageFooter",
          1
        ]
      ]
    }
  ],
  "debug_data_path": "debug_data\\CMPU 3010"
}